.gitignore
LICENSE
MANIFEST.in
README.md
django-userjs.sublime-project
django-userjs.sublime-workspace
setup.py
django_userjs.egg-info/PKG-INFO
django_userjs.egg-info/SOURCES.txt
django_userjs.egg-info/dependency_links.txt
django_userjs.egg-info/requires.txt
django_userjs.egg-info/top_level.txt
userjs/__init__.py
userjs/userjs_settings.py
userjs/utils.py
userjs/views.py
userjs/templatetags/__init__.py
userjs/templatetags/userjs.py