Metadata-Version: 1.1
Name: django-userjs
Version: 0.2
Summary: userjs is a Django application that produces javascript that represents a User
Home-page: https://github.com/tweekmonster/django-userjs
Author: Tommy Allen
Author-email: tommy@tweek.us
License: BSD
Platform: UNKNOWN
Classifier: Environment :: Web Environment
Classifier: Framework :: Django
Classifier: Intended Audience :: Developers
Classifier: License :: OSI Approved :: BSD License
Classifier: Operating System :: OS Independent
Classifier: Programming Language :: Python
Classifier: Programming Language :: Python :: 2.7
Classifier: Programming Language :: Python :: 3
